ssh/__init__.py
ssh/client.py
ssh/exceptions.py
ssh/utils.py
ssh_anywhere-1.0.6.dist-info/LICENSE
ssh_anywhere-1.0.6.dist-info/METADATA
ssh_anywhere-1.0.6.dist-info/WHEEL
ssh_anywhere-1.0.6.dist-info/entry_points.txt
ssh_anywhere-1.0.6.dist-info/RECORD
