Metadata-Version: 2.3
Name: ssh-anywhere
Version: 1.0.6
Summary: High-performance SSH library with unified API for direct and jump host connections
License: MIT
Keywords: ssh,multiplexing,jump-host,networking,automation,remote,security
Author: Cyril Chabarot
Author-email: cyril@chabarot.fr
Requires-Python: >=3.8.1,<4.0.0
Classifier: Development Status :: 4 - Beta
Classifier: Intended Audience :: Developers
Classifier: Intended Audience :: System Administrators
Classifier: License :: OSI Approved :: MIT License
Classifier: Operating System :: OS Independent
Classifier: Programming Language :: Python :: 3
Classifier: Programming Language :: Python :: 3.9
Classifier: Programming Language :: Python :: 3.10
Classifier: Programming Language :: Python :: 3.11
Classifier: Programming Language :: Python :: 3.12
Classifier: Programming Language :: Python :: 3.13
Classifier: Programming Language :: Python :: 3.8
Classifier: Topic :: Internet
Classifier: Topic :: Security
Classifier: Topic :: Software Development :: Libraries :: Python Modules
Classifier: Topic :: System :: Networking
Classifier: Topic :: System :: Systems Administration
Project-URL: Documentation, https://github.com/wbx13/ssh#readme
Project-URL: Homepage, https://github.com/wbx13/ssh
Project-URL: Repository, https://github.com/wbx13/ssh
